odoo/addons/helpdesk_product/README.rst
odoo/addons/helpdesk_product/__init__.py
odoo/addons/helpdesk_product/__manifest__.py
odoo/addons/helpdesk_product/demo/helpdesk_product_demo.xml
odoo/addons/helpdesk_product/i18n/helpdesk_product.pot
odoo/addons/helpdesk_product/i18n/it.po
odoo/addons/helpdesk_product/i18n/pt.po
odoo/addons/helpdesk_product/i18n/pt_BR.po
odoo/addons/helpdesk_product/i18n/sv.po
odoo/addons/helpdesk_product/models/__init__.py
odoo/addons/helpdesk_product/models/helpdesk_ticket.py
odoo/addons/helpdesk_product/models/product.py
odoo/addons/helpdesk_product/readme/CONTRIBUTORS.md
odoo/addons/helpdesk_product/readme/DESCRIPTION.md
odoo/addons/helpdesk_product/static/description/icon.png
odoo/addons/helpdesk_product/static/description/index.html
odoo/addons/helpdesk_product/views/helpdesk_ticket_view.xml
odoo/addons/helpdesk_product/views/product_view.xml
odoo_addon_helpdesk_product-18.0.1.0.1.4.dist-info/METADATA
odoo_addon_helpdesk_product-18.0.1.0.1.4.dist-info/WHEEL
odoo_addon_helpdesk_product-18.0.1.0.1.4.dist-info/top_level.txt
odoo_addon_helpdesk_product-18.0.1.0.1.4.dist-info/RECORD
